g722_1_mod.cpython-37m-aarch64-linux-gnu.so
g722_1_mod-0.0.10.dist-info/top_level.txt
g722_1_mod-0.0.10.dist-info/RECORD
g722_1_mod-0.0.10.dist-info/LICENSE
g722_1_mod-0.0.10.dist-info/METADATA
g722_1_mod-0.0.10.dist-info/WHEEL
g722_1_mod.libs/libgcc_s-7393e603.so.1
g722_1_mod.libs/libstdc++-1b614e01.so.6.0.32
